{
  "result":
  [
    {
      "name": "100029_Rexburg_1",
      "geoEntity": "sector",
      "parentEntityName": "SN0029LTE_Rexburg",
      "grendParentName": "1A",
      "latitude": 37.94701600,
      "longitude": -121.29707300,
      "azimuth": 0
    },
    {
      "name": "100029_Rexburg_2",
      "geoEntity": "sector",
      "parentEntityName": "SN0029LTE_Rexburg",
      "grendParentName": "1A",
      "latitude": 37.94701600,
      "longitude": -121.29707300,
      "azimuth": 60
    },
    {
      "name": "100029_Rexburg_3",
      "geoEntity": "sector",
      "parentEntityName": "SN0029LTE_Rexburg",
      "grendParentName": "1A",
      "latitude": 37.94701600,
      "longitude": -121.29707300,
      "azimuth": 120
    },
    {
      "name": "100029_Rexburg_4",
      "geoEntity": "sector",
      "parentEntityName": "SN0029LTE_Rexburg",
      "grendParentName": "1A",
      "latitude": 37.94701600,
      "longitude": -121.29707300,
      "azimuth": 180
    },
    {
      "name": "100029_Rexburg_5",
      "geoEntity": "sector",
      "parentEntityName": "SN0029LTE_Rexburg",
      "grendParentName": "1A",
      "latitude": 37.94701600,
      "longitude": -121.29707300,
      "azimuth": 240
    },
    {
      "name": "100029_Rexburg_6",
      "geoEntity": "sector",
      "parentEntityName": "SN0029LTE_Rexburg",
      "grendParentName": "1A",
      "latitude": 37.94701600,
      "longitude": -121.29707300,
      "azimuth": 300
    },
    {
      "name": "100064_AmFallsSilo_1",
      "geoEntity": "sector",
      "parentEntityName": "SN0064LTE_AmFallsSilo",
      "grandParentEntityName": "1A",
      "latitude": 37.925090,
      "longitude": -121.309448,
      "azimuth": 30
    },
    {
      "name": "100064_AmFallsSilo_2",
      "geoEntity": "sector",
      "parentEntityName": "SN0064LTE_AmFallsSilo",
      "grandParentEntityName": "1A",
      "latitude": 37.925090,
      "longitude": -121.309448,
      "azimuth": 150
    },
    {
      "name": "100064_AmFallsSilo_3",
      "geoEntity": "sector",
      "parentEntityName": "SN0064LTE_AmFallsSilo",
      "grandParentEntityName": "1A",
      "latitude": 37.925090,
      "longitude": -121.309448,
      "azimuth": 270
    },
    {
      "name": "100099_TFCounty_1",
      "geoEntity": "sector",
      "parentEntityName": "SN0099LTE_TFCounty",
      "grandParentEntityName": "1A",
      "latitude": 37.936823,
      "longitude": -121.270473,
      "azimuth": 60
    },
    {
      "name": "100099_TFCounty_2",
      "geoEntity": "sector",
      "parentEntityName": "SN0099LTE_TFCounty",
      "grandParentEntityName": "1A",
      "latitude": 37.936823,
      "longitude": -121.270473,
      "azimuth": 150
    },
    {
      "name": "100099_TFCounty_3",
      "geoEntity": "sector",
      "parentEntityName": "SN0099LTE_TFCounty",
      "grandParentEntityName": "1A",
      "latitude": 37.936823,
      "longitude": -121.270473,
      "azimuth": 240
    },
    {
      "name": "100099_TFCounty_4",
      "geoEntity": "sector",
      "parentEntityName": "SN0099LTE_TFCounty",
      "grandParentEntityName": "1A",
      "latitude": 37.936823,
      "longitude": -121.270473,
      "azimuth": 330
    },
    {
      "name": "100008_MagicMall_1",
      "geoEntity": "sector",
      "parentEntityName": "SN0008LTE_MagicMall",
      "grandParentEntityName": "1B",
      "latitude": 37.664294,
      "longitude": -121.047581,
      "azimuth": 330
    },
    {
      "name": "100056_Blackfoot_1",
      "geoEntity": "sector",
      "parentEntityName": "SN0056LTE_Blackfoot",
      "grandParentEntityName": "1B",
      "latitude": 37.650765,
      "longitude": -121.010197,
      "azimuth": 30
    },
    {
      "name": "100056_Blackfoot_2",
      "geoEntity": "sector",
      "parentEntityName": "SN0056LTE_Blackfoot",
      "grandParentEntityName": "1B",
      "latitude": 37.650765,
      "longitude": -121.010197,
      "azimuth": 90
    },
    {
      "name": "100056_Blackfoot_3",
      "geoEntity": "sector",
      "parentEntityName": "SN0056LTE_Blackfoot",
      "grandParentEntityName": "1B",
      "latitude": 37.650765,
      "longitude": -121.010197,
      "azimuth": 150
    },
    {
      "name": "100056_Blackfoot_4",
      "geoEntity": "sector",
      "parentEntityName": "SN0056LTE_Blackfoot",
      "grandParentEntityName": "1B",
      "latitude": 37.650765,
      "longitude": -121.010197,
      "azimuth": 210
    },
    {
      "name": "100056_Blackfoot_5",
      "geoEntity": "sector",
      "parentEntityName": "SN0056LTE_Blackfoot",
      "grandParentEntityName": "1B",
      "latitude": 37.650765,
      "longitude": -121.010197,
      "azimuth": 270
    },
    {
      "name": "100056_Blackfoot_6",
      "geoEntity": "sector",
      "parentEntityName": "SN0056LTE_Blackfoot",
      "grandParentEntityName": "1B",
      "latitude": 37.650765,
      "longitude": -121.010197,
      "azimuth": 330
    },
    {
      "name": "100027_Rigby_1",
      "geoEntity": "sector",
      "parentEntityName": "SN0027LTE_Rigby",
      "grandParentEntityName": "1B",
      "latitude": 37.631528,
      "longitude": -121.025919,
      "azimuth": 0
    },
    {
      "name": "100027_Rigby_2",
      "geoEntity": "sector",
      "parentEntityName": "SN0027LTE_Rigby",
      "grandParentEntityName": "1B",
      "latitude": 37.631528,
      "longitude": -121.025919,
      "azimuth": 60
    },
    {
      "name": "100027_Rigby_3",
      "geoEntity": "sector",
      "parentEntityName": "SN0027LTE_Rigby",
      "grandParentEntityName": "1B",
      "latitude": 37.631528,
      "longitude": -121.025919,
      "azimuth": 120
    },
    {
      "name": "100027_Rigby_4",
      "geoEntity": "sector",
      "parentEntityName": "SN0027LTE_Rigby",
      "grandParentEntityName": "1B",
      "latitude": 37.631528,
      "longitude": -121.025919,
      "azimuth": 180
    },
    {
      "name": "100027_Rigby_5",
      "geoEntity": "sector",
      "parentEntityName": "SN0027LTE_Rigby",
      "grandParentEntityName": "1B",
      "latitude": 37.631528,
      "longitude": -121.025919,
      "azimuth": 240
    },
    {
      "name": "100027_Rigby_6",
      "geoEntity": "sector",
      "parentEntityName": "SN0027LTE_Rigby",
      "grandParentEntityName": "1B",
      "latitude": 37.631528,
      "longitude": -121.025919,
      "azimuth": 300
    },
    {
      "name": "100002_Hagerman_1",
      "geoEntity": "sector",
      "parentEntityName": "SN0002LTE_Hagerman",
      "grandParentEntityName": "1C",
      "latitude": 38.619836,
      "longitude": -121.484118,
      "azimuth": 180
    },
    {
      "name": "100010_TFHigh_1",
      "geoEntity": "sector",
      "parentEntityName": "SN0010LTE_TFHigh",
      "grandParentEntityName": "1C",
      "latitude": 38.595596,
      "longitude": -121.496478,
      "azimuth": 90
    },
    {
      "name": "100010_TFHigh_2",
      "geoEntity": "sector",
      "parentEntityName": "SN0010LTE_TFHigh",
      "grandParentEntityName": "1C",
      "latitude": 38.595596,
      "longitude": -121.496478,
      "azimuth": 210
    },
    {
      "name": "100010_TFHigh_3",
      "geoEntity": "sector",
      "parentEntityName": "SN0010LTE_TFHigh",
      "grandParentEntityName": "1C",
      "latitude": 38.595596,
      "longitude": -121.496478,
      "azimuth": 330
    },
    {
      "name": "100022_LambWeston_1",
      "geoEntity": "sector",
      "parentEntityName": "SN0022LTE_LambWeston",
      "grandParentEntityName": "1C",
      "latitude": 38.599977,
      "longitude": -121.449274,
      "azimuth": 270
    }
  ]
}
